medicure/__init__.py
medicure/core.py
medicure/data_structures.py
medicure/utils.py
medicure/version.py
medicure/cli/__init__.py
medicure/cli/base.py
medicure/cli/save.py
medicure/cli/treat.py
medicure/cli/types.py
medicure/cli/utils.py
medicure/typer_patch/__init__.py
medicure/typer_patch/core.py
medicure/typer_patch/param_type.patch
medicure-0.3.0.dist-info/LICENSE
medicure-0.3.0.dist-info/METADATA
medicure-0.3.0.dist-info/WHEEL
medicure-0.3.0.dist-info/entry_points.txt
medicure-0.3.0.dist-info/top_level.txt
medicure-0.3.0.dist-info/RECORD
