Metadata-Version: 2.1
Name: medicure
Version: 0.3.0
Summary: A cosmetic treatment for your media files: movies, TV shows and also their subtitles.
Home-page: https://github.com/alirezatheh/medicure
Author: Alireza Hosseini
Author-email: alirezatheh@gmail.com
Project-URL: Bug Tracker, https://github.com/alirezatheh/medicure/issues
Project-URL: Documentation, https://github.com/alirezatheh/medicure
Project-URL: Source Code, https://github.com/alirezatheh/medicure
Keywords: audio,video,videos,media,multimedia,movies,tv,tvshows,tv-shows,series,subtitle,subtitles,audio-processing,video-processing
Classifier: Topic :: Multimedia :: Video
Classifier: Topic :: Multimedia :: Sound/Audio
Classifier: Topic :: Other/Nonlisted Topic
Classifier: Development Status :: 5 - Production/Stable
Classifier: License :: OSI Approved :: MIT License
Classifier: Programming Language :: Python
Classifier: Programming Language :: Python :: 3
Classifier: Programming Language :: Python :: 3 :: Only
Classifier: Programming Language :: Python :: 3.8
Classifier: Programming Language :: Python :: 3.9
Classifier: Programming Language :: Python :: 3.10
Classifier: Programming Language :: Python :: 3.11
Classifier: Operating System :: OS Independent
Classifier: Intended Audience :: End Users/Desktop
Classifier: Intended Audience :: Developers
Classifier: Intended Audience :: Education
Requires-Python: >=3.8
License-File: LICENSE
Requires-Dist: tmdbsimple
Requires-Dist: pymediainfo
Requires-Dist: typer (==0.5.0)
Requires-Dist: click
Requires-Dist: rich-click (==1.5.2)
Requires-Dist: patch
Requires-Dist: docstring-parser
Provides-Extra: develop
Requires-Dist: pre-commit ; extra == 'develop'
Provides-Extra: documentation
Requires-Dist: sphinx ; extra == 'documentation'
Requires-Dist: furo ; extra == 'documentation'
Requires-Dist: sphinxcontrib-napoleon ; extra == 'documentation'
Requires-Dist: sphinx-copybutton ; extra == 'documentation'
Requires-Dist: sphinx-click ; extra == 'documentation'
Requires-Dist: docutils ; extra == 'documentation'
Requires-Dist: myst-parser ; extra == 'documentation'
Provides-Extra: test
Requires-Dist: pytest ; extra == 'test'
Requires-Dist: pytest-cov ; extra == 'test'
Requires-Dist: varname ; extra == 'test'
